LICENSE
MANIFEST.in
README.md
setup.py
abie/__init__.py
abie/clibabie.py
abie/data_io.py
abie/events.py
abie/integrator.py
abie/integrator_adams_bashforth.py
abie/integrator_euler.py
abie/integrator_gauss_radau15.py
abie/integrator_leap_frog.py
abie/integrator_runge_kutta.py
abie/integrator_wisdom_holman.py
abie/ode.py
abie/particle.py
abie/particles.py
abie/recorder.py
abie/snapshot_serialization.py
abie/tools.py
abie.egg-info/PKG-INFO
abie.egg-info/SOURCES.txt
abie.egg-info/dependency_links.txt
abie.egg-info/entry_points.txt
abie.egg-info/not-zip-safe
abie.egg-info/requires.txt
abie.egg-info/top_level.txt
src/Makefile
src/additional_forces.c
src/bodysystemcuda.cu
src/common.c
src/common.h
src/gpuforce.cu
src/helper_cuda.h
src/helper_string.h
src/integrator_gauss_radau15.c
src/integrator_gauss_radau15.h
src/integrator_runge_kutta.c
src/integrator_runge_kutta.h
src/integrator_wisdom_holman.c
src/integrator_wisdom_holman.h